odoo/addons/product_abc_classification/README.rst
odoo/addons/product_abc_classification/__init__.py
odoo/addons/product_abc_classification/__manifest__.py
odoo/addons/product_abc_classification/data/ir_cron.xml
odoo/addons/product_abc_classification/i18n/es.po
odoo/addons/product_abc_classification/i18n/fr.po
odoo/addons/product_abc_classification/i18n/hr.po
odoo/addons/product_abc_classification/i18n/it.po
odoo/addons/product_abc_classification/i18n/product_abc_classification.pot
odoo/addons/product_abc_classification/models/__init__.py
odoo/addons/product_abc_classification/models/abc_classification_level.py
odoo/addons/product_abc_classification/models/abc_classification_product_level.py
odoo/addons/product_abc_classification/models/abc_classification_profile.py
odoo/addons/product_abc_classification/models/product_category.py
odoo/addons/product_abc_classification/models/product_product.py
odoo/addons/product_abc_classification/models/product_template.py
odoo/addons/product_abc_classification/readme/CONTRIBUTORS.rst
odoo/addons/product_abc_classification/readme/DESCRIPTION.rst
odoo/addons/product_abc_classification/readme/USAGE.rst
odoo/addons/product_abc_classification/security/ir.model.access.csv
odoo/addons/product_abc_classification/static/description/icon.png
odoo/addons/product_abc_classification/static/description/index.html
odoo/addons/product_abc_classification/tests/__init__.py
odoo/addons/product_abc_classification/tests/common.py
odoo/addons/product_abc_classification/tests/test_abc_classification_manual_profile.py
odoo/addons/product_abc_classification/tests/test_abc_classification_product_level.py
odoo/addons/product_abc_classification/tests/test_abc_classification_profile.py
odoo/addons/product_abc_classification/tests/test_product.py
odoo/addons/product_abc_classification/views/abc_classification_product_level.xml
odoo/addons/product_abc_classification/views/abc_classification_profile.xml
odoo_addon_product_abc_classification-16.0.2.0.0.2.dist-info/METADATA
odoo_addon_product_abc_classification-16.0.2.0.0.2.dist-info/WHEEL
odoo_addon_product_abc_classification-16.0.2.0.0.2.dist-info/top_level.txt
odoo_addon_product_abc_classification-16.0.2.0.0.2.dist-info/RECORD
