Metadata-Version: 2.1
Name: odoo-addon-product_abc_classification
Version: 16.0.2.0.0.2
Summary: ABC classification for sales and warehouse management
Home-page: https://github.com/OCA/product-attribute
Author: ACSONE SA/NV, ForgeFlow, Odoo Community Association (OCA)
Author-email: support@odoo-community.org
License: AGPL-3
Classifier: Programming Language :: Python
Classifier: Framework :: Odoo
Classifier: Framework :: Odoo :: 16.0
Classifier: License :: OSI Approved :: GNU Affero General Public License v3
Requires-Python: >=3.10
Requires-Dist: odoo<16.1dev,>=16.0a
